odoo/addons/ambtu/README.md
odoo/addons/ambtu/__init__.py
odoo/addons/ambtu/__manifest__.py
odoo/addons/ambtu/i18n/ca_ES.po
odoo/addons/ambtu/i18n/es_ES.po
odoo/addons/ambtu/reports/external_layout_standard.xml
odoo/addons/ambtu/reports/report_invoice_document.xml
odoo/addons/ambtu/static/src/img/footer.png
odoo_addon_ambtu-16.0.2.0.6.dist-info/METADATA
odoo_addon_ambtu-16.0.2.0.6.dist-info/WHEEL
odoo_addon_ambtu-16.0.2.0.6.dist-info/top_level.txt
odoo_addon_ambtu-16.0.2.0.6.dist-info/RECORD
