Metadata-Version: 2.1
Name: odoo-addon-ambtu
Version: 16.0.2.0.6
Summary: AmbTu module customizations
Home-page: https://git.coopdevs.org/coopdevs/odoo/odoo-addons/odoo-ambtu
Author: Coopdevs Treball SCCL
License: AGPL-3
Platform: UNKNOWN
Classifier: Programming Language :: Python
Classifier: Framework :: Odoo
Classifier: Framework :: Odoo :: 16.0
Classifier: License :: OSI Approved :: GNU Affero General Public License v3
Requires-Python: >=3.10
Requires-Dist: odoo <16.1dev,>=16.0a
